earthkit/__init__.py
earthkit/utils/__init__.py
earthkit/utils/_version.py
earthkit/utils/module.py
earthkit/utils/testing.py
earthkit/utils/array/__init__.py
earthkit/utils/array/backend.py
earthkit/utils/array/compute.py
earthkit/utils/array/convert.py
earthkit/utils/array/device.py
earthkit/utils/array/dtype.py
earthkit/utils/array/namespace/cupy.py
earthkit/utils/array/namespace/numpy.py
earthkit/utils/array/namespace/torch.py
earthkit_utils-0.1.2.dist-info/licenses/LICENSE
earthkit_utils-0.1.2.dist-info/METADATA
earthkit_utils-0.1.2.dist-info/WHEEL
earthkit_utils-0.1.2.dist-info/top_level.txt
earthkit_utils-0.1.2.dist-info/RECORD
